[
  {
    "line": 1,
    "elements": [
      {
        "start_timestamp": "2021-04-09T11:56:50.821Z",
        "before": [
          {
            "result": {
              "duration": 4663434270,
              "status": "passed"
            },
            "match": {
              "location": "Hook.hookUp(Scenario)"
            }
          }
        ],
        "line": 4,
        "name": "As a registered user, user should be able to logged in",
        "description": "",
        "id": "validate-user-login-functionality;as-a-registered-user--user-should-be-able-to-logged-in",
        "after": [
          {
            "result": {
              "duration": 283171732,
              "status": "passed"
            },
            "match": {
              "location": "Hook.teardown(Scenario)"
            }
          }
        ],
        "type": "scenario",
        "keyword": "Scenario",
        "steps": [
          {
            "result": {
              "duration": 14802252906,
              "status": "passed"
            },
            "line": 5,
            "name": "User has launched the webpage",
            "match": {
              "location": "HomeStepDefinition.user_has_launched_the_webpage()"
            },
            "keyword": "Given "
          },
          {
            "result": {
              "duration": 5551686970,
              "status": "passed"
            },
            "line": 6,
            "name": "User navigates to login page",
            "match": {
              "location": "HomeStepDefinition.navigateToLoginFromHome()"
            },
            "keyword": "When "
          },
          {
            "result": {
              "duration": 11871663454,
              "status": "passed"
            },
            "line": 7,
            "name": "User enters login details smrj47@gmail.com and dpgAutomation_",
            "match": {
              "arguments": [
                {
                  "val": "smrj47@gmail.com",
                  "offset": 26
                },
                {
                  "val": "dpgAutomation_",
                  "offset": 47
                }
              ],
              "location": "LoginStepDefinition.userEntersLoginDetails(String,String)"
            },
            "keyword": "And "
          },
          {
            "result": {
              "duration": 1317520390,
              "status": "passed"
            },
            "line": 8,
            "name": "User should be able to login successfully with smrj47@gmail.com",
            "match": {
              "arguments": [
                {
                  "val": "smrj47@gmail.com",
                  "offset": 47
                }
              ],
              "location": "LoginStepDefinition.loginSuccess(String)"
            },
            "keyword": "Then "
          }
        ],
        "tags": [
          {
            "name": "@Regression"
          },
          {
            "name": "@Login"
          }
        ]
      }
    ],
    "name": "Validate user login functionality",
    "description": "",
    "id": "validate-user-login-functionality",
    "keyword": "Feature",
    "uri": "file:src/test/java/Features/ValidateLogin.feature",
    "tags": []
  }
]